src/__init__.py
src/cli.py
src/abs/__init__.py
src/abs/cell.py
src/abs/game.py
src/abs/map.py
src/abs/unit.py
src/commands/__init__.py
src/commands/cmd_generate.py
sudokucli-0.1.2.dist-info/METADATA
sudokucli-0.1.2.dist-info/RECORD
sudokucli-0.1.2.dist-info/WHEEL
sudokucli-0.1.2.dist-info/entry_points.txt
sudokucli-0.1.2.dist-info/top_level.txt
sudokucli-0.1.2.dist-info/zip-safe
