Metadata-Version: 2.1
Name: sudokucli
Version: 0.1.2
Summary: Console 9*9 Sudoku Game
Home-page: https://github.com/a2htray/sudoku-cli
Author: a2htray
Author-email: a2htray.yuen@gmail.com
License: Apache License 2.0
Platform: UNKNOWN
Requires-Dist: click
